{"chunk_definitions":[{"chunk_id":"c9qma0dnswrky","chunk_label":"getData","document_id":"547B6CBB","expansion_state":0,"options":{"engine":"r","eval":false,"label":"getData"},"row":14,"row_count":1,"visible":true},{"chunk_id":"c4a9ol9pzk4at","chunk_label":"unnamed-chunk-1","document_id":"547B6CBB","expansion_state":0,"options":{"engine":"r","label":"unnamed-chunk-18"},"row":19,"row_count":1,"visible":true},{"chunk_id":"cmcejhxt9bn1u","chunk_label":"unnamed-chunk-2","document_id":"547B6CBB","expansion_state":0,"options":{"engine":"r","label":"unnamed-chunk-3"},"row":23,"row_count":1,"visible":true},{"chunk_id":"cqqxn4pth4oin","chunk_label":"unnamed-chunk-3","document_id":"547B6CBB","expansion_state":0,"options":{"engine":"r","label":"unnamed-chunk-4"},"row":27,"row_count":1,"visible":true},{"chunk_id":"coq3fwv6emxmd","chunk_label":"unnamed-chunk-4","document_id":"547B6CBB","expansion_state":0,"options":{"engine":"r","label":"unnamed-chunk-5"},"row":31,"row_count":1,"visible":true},{"chunk_id":"c1l9oijs9pagq","chunk_label":"unnamed-chunk-5","document_id":"547B6CBB","expansion_state":0,"options":{"engine":"r","label":"unnamed-chunk-6"},"row":36,"row_count":1,"visible":true},{"chunk_id":"c8yjwbc20g20g","chunk_label":"unnamed-chunk-6","document_id":"547B6CBB","expansion_state":0,"options":{"engine":"r","label":"unnamed-chunk-7"},"row":41,"row_count":1,"visible":true},{"chunk_id":"cvupv0mcbwqvn","chunk_label":"unnamed-chunk-7","document_id":"547B6CBB","expansion_state":0,"options":{"engine":"r","label":"unnamed-chunk-8"},"row":45,"row_count":1,"visible":true},{"chunk_id":"c61z5c966l9v2","chunk_label":"unnamed-chunk-8","document_id":"547B6CBB","expansion_state":0,"options":{"engine":"r","label":"unnamed-chunk-9"},"row":55,"row_count":1,"visible":true},{"chunk_id":"cdnx6ohused6e","chunk_label":"unnamed-chunk-9","document_id":"547B6CBB","expansion_state":0,"options":{"engine":"r","label":"unnamed-chunk-10"},"row":72,"row_count":1,"visible":true},{"chunk_id":"ckx7lj64i0w59","chunk_label":"unnamed-chunk-10","document_id":"547B6CBB","expansion_state":0,"options":{"engine":"r","label":"unnamed-chunk-11"},"row":77,"row_count":1,"visible":true},{"chunk_id":"cf2x1bfd8vdrc","chunk_label":"unnamed-chunk-11","document_id":"547B6CBB","expansion_state":0,"options":{"engine":"r","label":"unnamed-chunk-12"},"row":84,"row_count":1,"visible":true},{"chunk_id":"ca05zu6wgdass","chunk_label":"unnamed-chunk-12","document_id":"547B6CBB","expansion_state":0,"options":{"engine":"r","label":"unnamed-chunk-13"},"row":87,"row_count":1,"visible":true},{"chunk_id":"cfbcwo6oqvq5s","chunk_label":"unnamed-chunk-13","document_id":"547B6CBB","expansion_state":0,"options":{"engine":"r","label":"unnamed-chunk-14"},"row":97,"row_count":1,"visible":true},{"chunk_id":"cjjf9xij1m8h2","chunk_label":"unnamed-chunk-14","document_id":"547B6CBB","expansion_state":0,"options":{"engine":"r","label":"unnamed-chunk-15"},"row":115,"row_count":1,"visible":true},{"chunk_id":"coafitf7pq2nx","chunk_label":"unnamed-chunk-15","document_id":"547B6CBB","expansion_state":0,"options":{"engine":"r","label":"unnamed-chunk-16"},"row":120,"row_count":1,"visible":true}],"doc_write_time":1548281753}